[
    {
        "logics": [
            {
                "logicsInfo": [
                    {
                        "id": 1,
                        "attr": 1,
                        "modelType": "SceneDeal",
                        "content": "{\"SceneItemInfo\":[{\"state\":\"00000001\",\"id\":1,\"pid\":0,\"type\":\"3.0_logic\",\"address\":\"FE400005\",\"opt\":\"00000000\",\"optName\":\"逻辑关闭\",\"delay\":0},{\"state\":\"00000001\",\"id\":2,\"pid\":905444872,\"type\":\"4.0_scene\",\"address\":\"FE100046\",\"opt\":\"00000001\",\"optName\":\"场景调用\",\"delay\":0},{\"state\":\"00000001\",\"id\":3,\"pid\":0,\"type\":\"6.1_panel\",\"address\":\"FE300006\",\"opt\":\"00000000\",\"optName\":\"禁止面板触发\",\"delay\":0},{\"state\":\"00828282\",\"id\":4,\"pid\":0,\"type\":\"13.0_RGB\",\"address\":\"FE000C06\",\"opt\":\"00000000\",\"optName\":\"调色\",\"delay\":0},{\"state\":\"00000002\",\"id\":5,\"pid\":0,\"type\":\"10.0_key\",\"address\":\"FE000C00\",\"opt\":\"\",\"optName\":\"\",\"delay\":0},{\"state\":\"00000000\",\"id\":6,\"pid\":0,\"type\":\"1.0_switch\",\"address\":\"FE000C01\",\"opt\":\"00000001\",\"optName\":\"开启\",\"delay\":0},{\"state\":\"10000030\",\"id\":7,\"pid\":0,\"type\":\"2.0_dimmer\",\"address\":\"FE000C02\",\"opt\":\"\",\"optName\":\"\",\"delay\":0},{\"state\":\"10000077\",\"id\":8,\"pid\":0,\"type\":\"2.1_dimmer\",\"address\":\"FE000C03\",\"opt\":\"\",\"optName\":\"\",\"delay\":0},{\"state\":\"00000051\",\"id\":9,\"pid\":0,\"type\":\"7.0_ir\",\"address\":\"FE000C04\",\"opt\":\"\",\"optName\":\"\",\"delay\":0},{\"state\":\"00000038\",\"id\":10,\"pid\":0,\"type\":\"8.0_uart\",\"address\":\"FE000C05\",\"opt\":\"\",\"optName\":\"\",\"delay\":0},{\"state\":\"00655B46\",\"id\":11,\"pid\":0,\"type\":\"13.0_RGB\",\"address\":\"FE000C06\",\"opt\":\"\",\"optName\":\"\",\"delay\":0},{\"state\":\"00007829\",\"id\":12,\"pid\":0,\"type\":\"14.0_data\",\"address\":\"FE000C07\",\"opt\":\"\",\"optName\":\"\",\"delay\":0},{\"state\":\"00000000\",\"id\":13,\"pid\":911148722,\"type\":\"1.0_switch\",\"address\":\"FE000208\",\"opt\":\"00000001\",\"optName\":\"开启\",\"delay\":0},{\"state\":\"00000000\",\"id\":14,\"pid\":342508859,\"type\":\"1.0_switch\",\"address\":\"FE000308\",\"opt\":\"00000001\",\"optName\":\"开启\",\"delay\":0},{\"state\":\"00000000\",\"id\":15,\"pid\":125732438,\"type\":\"1.0_switch\",\"address\":\"FE000A03\",\"opt\":\"00000001\",\"optName\":\"开启\",\"delay\":0},{\"state\":\"00000000\",\"id\":16,\"pid\":261103593,\"type\":\"1.0_switch\",\"address\":\"FE000A04\",\"opt\":\"00000001\",\"optName\":\"开启\",\"delay\":0},{\"state\":\"00000000\",\"id\":17,\"pid\":327701176,\"type\":\"1.0_switch\",\"address\":\"FE000A01\",\"opt\":\"00000001\",\"optName\":\"开启\",\"delay\":0},{\"state\":\"00000000\",\"id\":18,\"pid\":741863729,\"type\":\"1.0_switch\",\"address\":\"FE000A02\",\"opt\":\"00000001\",\"optName\":\"开启\",\"delay\":0},{\"state\":\"00000000\",\"id\":19,\"pid\":726368415,\"type\":\"1.0_switch\",\"address\":\"FE000207\",\"opt\":\"00000001\",\"optName\":\"开启\",\"delay\":0},{\"state\":\"00000000\",\"id\":20,\"pid\":911148722,\"type\":\"1.0_switch\",\"address\":\"FE000208\",\"opt\":\"00000001\",\"optName\":\"开启\",\"delay\":0},{\"state\":\"00000000\",\"id\":21,\"pid\":342508859,\"type\":\"1.0_switch\",\"address\":\"FE000308\",\"opt\":\"00000001\",\"optName\":\"开启\",\"delay\":0},{\"state\":\"00000000\",\"id\":22,\"pid\":125732438,\"type\":\"1.0_switch\",\"address\":\"FE000A03\",\"opt\":\"00000001\",\"optName\":\"开启\",\"delay\":0},{\"state\":\"00000000\",\"id\":23,\"pid\":261103593,\"type\":\"1.0_switch\",\"address\":\"FE000A04\",\"opt\":\"00000001\",\"optName\":\"开启\",\"delay\":0},{\"state\":\"00000000\",\"id\":24,\"pid\":327701176,\"type\":\"1.0_switch\",\"address\":\"FE000A01\",\"opt\":\"00000001\",\"optName\":\"开启\",\"delay\":0},{\"state\":\"00000000\",\"id\":25,\"pid\":741863729,\"type\":\"1.0_switch\",\"address\":\"FE000A02\",\"opt\":\"00000001\",\"optName\":\"开启\",\"delay\":0},{\"state\":\"00000000\",\"id\":26,\"pid\":726368415,\"type\":\"1.0_switch\",\"address\":\"FE000207\",\"opt\":\"00000001\",\"optName\":\"开启\",\"delay\":0},{\"state\":\"00000000\",\"id\":27,\"pid\":911148722,\"type\":\"1.0_switch\",\"address\":\"FE000208\",\"opt\":\"00000001\",\"optName\":\"开启\",\"delay\":0},{\"state\":\"00000000\",\"id\":28,\"pid\":342508859,\"type\":\"1.0_switch\",\"address\":\"FE000308\",\"opt\":\"00000001\",\"optName\":\"开启\",\"delay\":0},{\"state\":\"00000000\",\"id\":29,\"pid\":125732438,\"type\":\"1.0_switch\",\"address\":\"FE000A03\",\"opt\":\"00000001\",\"optName\":\"开启\",\"delay\":0},{\"state\":\"00000000\",\"id\":30,\"pid\":261103593,\"type\":\"1.0_switch\",\"address\":\"FE000A04\",\"opt\":\"00000001\",\"optName\":\"开启\",\"delay\":0},{\"state\":\"00000000\",\"id\":31,\"pid\":327701176,\"type\":\"1.0_switch\",\"address\":\"FE000A01\",\"opt\":\"00000001\",\"optName\":\"开启\",\"delay\":0},{\"state\":\"00000000\",\"id\":32,\"pid\":741863729,\"type\":\"1.0_switch\",\"address\":\"FE000A02\",\"opt\":\"00000001\",\"optName\":\"开启\",\"delay\":0},{\"state\":\"00000000\",\"id\":33,\"pid\":726368415,\"type\":\"1.0_switch\",\"address\":\"FE000207\",\"opt\":\"00000001\",\"optName\":\"开启\",\"delay\":0},{\"state\":\"00000000\",\"id\":34,\"pid\":911148722,\"type\":\"1.0_switch\",\"address\":\"FE000208\",\"opt\":\"00000001\",\"optName\":\"开启\",\"delay\":0},{\"state\":\"00000000\",\"id\":35,\"pid\":342508859,\"type\":\"1.0_switch\",\"address\":\"FE000308\",\"opt\":\"00000001\",\"optName\":\"开启\",\"delay\":0},{\"state\":\"00000000\",\"id\":36,\"pid\":125732438,\"type\":\"1.0_switch\",\"address\":\"FE000A03\",\"opt\":\"00000001\",\"optName\":\"开启\",\"delay\":0},{\"state\":\"00000000\",\"id\":37,\"pid\":261103593,\"type\":\"1.0_switch\",\"address\":\"FE000A04\",\"opt\":\"00000001\",\"optName\":\"开启\",\"delay\":0},{\"state\":\"00000000\",\"id\":38,\"pid\":327701176,\"type\":\"1.0_switch\",\"address\":\"FE000A01\",\"opt\":\"00000001\",\"optName\":\"开启\",\"delay\":0},{\"state\":\"00000000\",\"id\":39,\"pid\":741863729,\"type\":\"1.0_switch\",\"address\":\"FE000A02\",\"opt\":\"00000001\",\"optName\":\"开启\",\"delay\":0},{\"state\":\"00000000\",\"id\":40,\"pid\":726368415,\"type\":\"1.0_switch\",\"address\":\"FE000207\",\"opt\":\"00000001\",\"optName\":\"开启\",\"delay\":0},{\"state\":\"00000000\",\"id\":41,\"pid\":911148722,\"type\":\"1.0_switch\",\"address\":\"FE000208\",\"opt\":\"00000001\",\"optName\":\"开启\",\"delay\":0},{\"state\":\"00000000\",\"id\":42,\"pid\":342508859,\"type\":\"1.0_switch\",\"address\":\"FE000308\",\"opt\":\"00000001\",\"optName\":\"开启\",\"delay\":0},{\"state\":\"00000000\",\"id\":43,\"pid\":125732438,\"type\":\"1.0_switch\",\"address\":\"FE000A03\",\"opt\":\"00000001\",\"optName\":\"开启\",\"delay\":0},{\"state\":\"00000000\",\"id\":44,\"pid\":261103593,\"type\":\"1.0_switch\",\"address\":\"FE000A04\",\"opt\":\"00000001\",\"optName\":\"开启\",\"delay\":0},{\"state\":\"00000000\",\"id\":45,\"pid\":327701176,\"type\":\"1.0_switch\",\"address\":\"FE000A01\",\"opt\":\"00000001\",\"optName\":\"开启\",\"delay\":0},{\"state\":\"00000000\",\"id\":46,\"pid\":741863729,\"type\":\"1.0_switch\",\"address\":\"FE000A02\",\"opt\":\"00000001\",\"optName\":\"开启\",\"delay\":0},{\"state\":\"00000000\",\"id\":47,\"pid\":726368415,\"type\":\"1.0_switch\",\"address\":\"FE000207\",\"opt\":\"00000001\",\"optName\":\"开启\",\"delay\":0},{\"state\":\"00000000\",\"id\":48,\"pid\":911148722,\"type\":\"1.0_switch\",\"address\":\"FE000208\",\"opt\":\"00000001\",\"optName\":\"开启\",\"delay\":0},{\"state\":\"00000000\",\"id\":49,\"pid\":342508859,\"type\":\"1.0_switch\",\"address\":\"FE000308\",\"opt\":\"00000001\",\"optName\":\"开启\",\"delay\":0},{\"state\":\"00000000\",\"id\":50,\"pid\":125732438,\"type\":\"1.0_switch\",\"address\":\"FE000A03\",\"opt\":\"00000001\",\"optName\":\"开启\",\"delay\":0},{\"state\":\"00000000\",\"id\":51,\"pid\":261103593,\"type\":\"1.0_switch\",\"address\":\"FE000A04\",\"opt\":\"00000001\",\"optName\":\"开启\",\"delay\":0},{\"state\":\"00000000\",\"id\":52,\"pid\":327701176,\"type\":\"1.0_switch\",\"address\":\"FE000A01\",\"opt\":\"00000001\",\"optName\":\"开启\",\"delay\":0},{\"state\":\"00000000\",\"id\":53,\"pid\":741863729,\"type\":\"1.0_switch\",\"address\":\"FE000A02\",\"opt\":\"00000001\",\"optName\":\"开启\",\"delay\":0}],\"pid\":723710772}"
                    }
                ],
                "id": 1,
                "pid": 876274720
            },
            {
                "logicsInfo": [
                    {
                        "id": 1,
                        "attr": 1,
                        "modelType": "VoiceDeal",
                        "content": null
                    },
                    {
                        "id": 2,
                        "attr": 1,
                        "modelType": "VoiceDeal",
                        "content": "{\"voiceItem\":[{\"letter\":\"A\",\"pid\":0,\"type\":null,\"address\":null},{\"letter\":\"B\",\"pid\":0,\"type\":null,\"address\":null},{\"letter\":\"C\",\"pid\":0,\"type\":null,\"address\":null},{\"letter\":\"D\",\"pid\":0,\"type\":null,\"address\":null},{\"letter\":\"E\",\"pid\":0,\"type\":null,\"address\":null},{\"letter\":\"F\",\"pid\":0,\"type\":null,\"address\":null},{\"letter\":\"G\",\"pid\":0,\"type\":null,\"address\":null},{\"letter\":\"H\",\"pid\":0,\"type\":null,\"address\":null}],\"voiceIfItem\":[{\"result\":null,\"id\":1,\"pid\":0,\"type\":null,\"address\":null,\"opt\":null,\"optName\":null,\"delay\":0},{\"result\":null,\"id\":2,\"pid\":0,\"type\":null,\"address\":null,\"opt\":null,\"optName\":null,\"delay\":0},{\"result\":null,\"id\":3,\"pid\":0,\"type\":null,\"address\":null,\"opt\":null,\"optName\":null,\"delay\":0},{\"result\":null,\"id\":4,\"pid\":0,\"type\":null,\"address\":null,\"opt\":null,\"optName\":null,\"delay\":0},{\"result\":null,\"id\":5,\"pid\":0,\"type\":null,\"address\":null,\"opt\":null,\"optName\":null,\"delay\":0},{\"result\":null,\"id\":6,\"pid\":0,\"type\":null,\"address\":null,\"opt\":null,\"optName\":null,\"delay\":0},{\"result\":null,\"id\":7,\"pid\":0,\"type\":null,\"address\":null,\"opt\":null,\"optName\":null,\"delay\":0},{\"result\":null,\"id\":8,\"pid\":0,\"type\":null,\"address\":null,\"opt\":null,\"optName\":null,\"delay\":0},{\"result\":null,\"id\":9,\"pid\":0,\"type\":null,\"address\":null,\"opt\":null,\"optName\":null,\"delay\":0},{\"result\":null,\"id\":10,\"pid\":0,\"type\":null,\"address\":null,\"opt\":null,\"optName\":null,\"delay\":0},{\"result\":null,\"id\":11,\"pid\":0,\"type\":null,\"address\":null,\"opt\":null,\"optName\":null,\"delay\":0},{\"result\":null,\"id\":12,\"pid\":0,\"type\":null,\"address\":null,\"opt\":null,\"optName\":null,\"delay\":0}],\"voice\":\"A+B+C\",\"voiceGive\":\"FEFB0305\"}"
                    }
                ],
                "id": 2,
                "pid": 221313098
            },
            {
                "logicsInfo": [
                    {
                        "id": 1,
                        "attr": 1,
                        "modelType": "ConditionDeal",
                        "content": "{\"conditionInfo\":[{\"id\":1,\"a\":1,\"objPid\":0,\"objAddress\":\"FE000C00\",\"objType\":\"10.0_key\",\"b\":0,\"operation\":null,\"c\":1,\"comparePid\":0,\"compareobjAddress\":null,\"compareobjType\":null,\"d\":0},{\"id\":2,\"a\":1,\"objPid\":0,\"objAddress\":\"FE000C01\",\"objType\":\"1.0_switch\",\"b\":0,\"operation\":null,\"c\":1,\"comparePid\":0,\"compareobjAddress\":null,\"compareobjType\":null,\"d\":0},{\"id\":3,\"a\":1,\"objPid\":0,\"objAddress\":\"FE000C03\",\"objType\":\"2.1_dimmer\",\"b\":0,\"operation\":null,\"c\":1,\"comparePid\":0,\"compareobjAddress\":null,\"compareobjType\":null,\"d\":0},{\"id\":4,\"a\":1,\"objPid\":0,\"objAddress\":\"FE000C02\",\"objType\":\"2.0_dimmer\",\"b\":0,\"operation\":null,\"c\":1,\"comparePid\":0,\"compareobjAddress\":null,\"compareobjType\":null,\"d\":0},{\"id\":5,\"a\":1,\"objPid\":0,\"objAddress\":\"FE000C04\",\"objType\":\"7.0_ir\",\"b\":0,\"operation\":null,\"c\":1,\"comparePid\":0,\"compareobjAddress\":null,\"compareobjType\":null,\"d\":0},{\"id\":6,\"a\":1,\"objPid\":0,\"objAddress\":\"FE000C05\",\"objType\":\"8.0_uart\",\"b\":0,\"operation\":null,\"c\":1,\"comparePid\":0,\"compareobjAddress\":null,\"compareobjType\":null,\"d\":0},{\"id\":7,\"a\":1,\"objPid\":0,\"objAddress\":\"FE000C06\",\"objType\":\"13.0_RGB\",\"b\":0,\"operation\":null,\"c\":1,\"comparePid\":0,\"compareobjAddress\":null,\"compareobjType\":null,\"d\":0},{\"id\":8,\"a\":1,\"objPid\":0,\"objAddress\":\"FE000C07\",\"objType\":\"14.0_data\",\"b\":0,\"operation\":null,\"c\":1,\"comparePid\":0,\"compareobjAddress\":null,\"compareobjType\":null,\"d\":0},{\"id\":9,\"a\":1,\"objPid\":0,\"objAddress\":\"FEF80C03\",\"objType\":\"10.2_io\",\"b\":0,\"operation\":null,\"c\":1,\"comparePid\":0,\"compareobjAddress\":null,\"compareobjType\":null,\"d\":0},{\"id\":10,\"a\":1,\"objPid\":221313098,\"objAddress\":\"FE400002\",\"objType\":\"3.0_logic\",\"b\":0,\"operation\":null,\"c\":1,\"comparePid\":0,\"compareobjAddress\":null,\"compareobjType\":null,\"d\":0},{\"id\":11,\"a\":1,\"objPid\":856985173,\"objAddress\":\"FE100002\",\"objType\":\"4.0_scene\",\"b\":0,\"operation\":null,\"c\":1,\"comparePid\":0,\"compareobjAddress\":null,\"compareobjType\":null,\"d\":0},{\"id\":12,\"a\":1,\"objPid\":499192175,\"objAddress\":\"FE200001\",\"objType\":\"5.0_timer\",\"b\":0,\"operation\":null,\"c\":1,\"comparePid\":0,\"compareobjAddress\":null,\"compareobjType\":null,\"d\":0},{\"id\":13,\"a\":1,\"objPid\":540085328,\"objAddress\":\"FE300001\",\"objType\":\"6.1_panel\",\"b\":0,\"operation\":null,\"c\":1,\"comparePid\":0,\"compareobjAddress\":null,\"compareobjType\":null,\"d\":0},{\"id\":14,\"a\":1,\"objPid\":0,\"objAddress\":\"FE300457\",\"objType\":\"6.2_sensor\",\"b\":0,\"operation\":null,\"c\":1,\"comparePid\":0,\"compareobjAddress\":null,\"compareobjType\":null,\"d\":0},{\"id\":15,\"a\":1,\"objPid\":643992081,\"objAddress\":\"FEFB0301\",\"objType\":\"9.0_virtualport\",\"b\":0,\"operation\":null,\"c\":1,\"comparePid\":0,\"compareobjAddress\":null,\"compareobjType\":null,\"d\":0},{\"id\":16,\"a\":1,\"objPid\":0,\"objAddress\":\"FEF9000C\",\"objType\":\"15.0_LocalVariable\",\"b\":0,\"operation\":null,\"c\":1,\"comparePid\":0,\"compareobjAddress\":null,\"compareobjType\":null,\"d\":0},{\"id\":17,\"a\":1,\"objPid\":0,\"objAddress\":\"FEFB0002\",\"objType\":\"17.0_Date\",\"b\":0,\"operation\":null,\"c\":1,\"comparePid\":0,\"compareobjAddress\":null,\"compareobjType\":null,\"d\":0},{\"id\":18,\"a\":1,\"objPid\":0,\"objAddress\":\"FEFB0003\",\"objType\":\"18.0_Time\",\"b\":0,\"operation\":null,\"c\":1,\"comparePid\":0,\"compareobjAddress\":null,\"compareobjType\":null,\"d\":0}],\"trueDo\":[{\"id\":1,\"pid\":856985173,\"type\":\"4.0_scene\",\"address\":\"FE100002\",\"opt\":\"00000001\",\"optName\":\"场景调用\",\"delay\":0},{\"id\":2,\"pid\":319694443,\"type\":\"4.0_scene\",\"address\":\"FE100003\",\"opt\":\"00000001\",\"optName\":\"场景调用\",\"delay\":0},{\"id\":3,\"pid\":0,\"type\":null,\"address\":null,\"opt\":null,\"optName\":null,\"delay\":0},{\"id\":4,\"pid\":0,\"type\":null,\"address\":null,\"opt\":null,\"optName\":null,\"delay\":0},{\"id\":5,\"pid\":0,\"type\":null,\"address\":null,\"opt\":null,\"optName\":null,\"delay\":0},{\"id\":6,\"pid\":0,\"type\":null,\"address\":null,\"opt\":null,\"optName\":null,\"delay\":0},{\"id\":7,\"pid\":319694443,\"type\":\"4.0_scene\",\"address\":\"FE100003\",\"opt\":\"\",\"optName\":\"\",\"delay\":0},{\"id\":8,\"pid\":0,\"type\":null,\"address\":null,\"opt\":null,\"optName\":null,\"delay\":0}],\"falseDo\":[{\"id\":1,\"pid\":142676410,\"type\":\"1.0_switch\",\"address\":\"FE000302\",\"opt\":\"00000001\",\"optName\":\"开启\",\"delay\":0},{\"id\":2,\"pid\":892313590,\"type\":\"1.0_switch\",\"address\":\"FE000303\",\"opt\":\"00000001\",\"optName\":\"开启\",\"delay\":0},{\"id\":3,\"pid\":0,\"type\":null,\"address\":null,\"opt\":null,\"optName\":null,\"delay\":0},{\"id\":4,\"pid\":0,\"type\":null,\"address\":null,\"opt\":null,\"optName\":null,\"delay\":0},{\"id\":5,\"pid\":0,\"type\":null,\"address\":null,\"opt\":null,\"optName\":null,\"delay\":0},{\"id\":6,\"pid\":0,\"type\":null,\"address\":null,\"opt\":null,\"optName\":null,\"delay\":0},{\"id\":7,\"pid\":0,\"type\":null,\"address\":null,\"opt\":null,\"optName\":null,\"delay\":0},{\"id\":8,\"pid\":0,\"type\":null,\"address\":null,\"opt\":null,\"optName\":null,\"delay\":0},{\"id\":9,\"pid\":169859417,\"type\":\"1.0_switch\",\"address\":\"FE000503\",\"opt\":\"\",\"optName\":\"\",\"delay\":0},{\"id\":10,\"pid\":0,\"type\":null,\"address\":null,\"opt\":null,\"optName\":null,\"delay\":0}]}"
                    },
                    {
                        "id": 2,
                        "attr": 0,
                        "modelType": "ConditionDeal",
                        "content": "{\"conditionInfo\":[{\"id\":1,\"a\":1,\"objPid\":643992081,\"objAddress\":\"FEFB0301\",\"objType\":\"9.0_virtualport\",\"b\":0,\"operation\":\">=\",\"c\":1,\"comparePid\":221313098,\"compareobjAddress\":\"FE400002\",\"compareobjType\":\"3.0_logic\",\"d\":0},{\"id\":2,\"a\":1,\"objPid\":319694443,\"objAddress\":\"FE100003\",\"objType\":\"4.0_scene\",\"b\":0,\"operation\":\"==\",\"c\":1,\"comparePid\":537371480,\"compareobjAddress\":\"FE000404\",\"compareobjType\":\"1.0_switch\",\"d\":0},{\"id\":3,\"a\":1,\"objPid\":0,\"objAddress\":\"FEFB0002\",\"objType\":\"17.0_Date\",\"b\":0,\"operation\":\"==\",\"c\":1,\"comparePid\":0,\"compareobjAddress\":\"FFFF0616\",\"compareobjType\":\"\",\"d\":0},{\"id\":4,\"a\":1,\"objPid\":0,\"objAddress\":\"FEFB0003\",\"objType\":\"18.0_Time\",\"b\":0,\"operation\":\"==\",\"c\":1,\"comparePid\":0,\"compareobjAddress\":\"00040C00\",\"compareobjType\":\"\",\"d\":0},{\"id\":5,\"a\":1,\"objPid\":0,\"objAddress\":\"FE300002\",\"objType\":\"6.1_panel\",\"b\":0,\"operation\":null,\"c\":1,\"comparePid\":0,\"compareobjAddress\":null,\"compareobjType\":null,\"d\":0},{\"id\":6,\"a\":1,\"objPid\":0,\"objAddress\":null,\"objType\":null,\"b\":0,\"operation\":null,\"c\":1,\"comparePid\":0,\"compareobjAddress\":null,\"compareobjType\":null,\"d\":0}],\"trueDo\":[{\"id\":1,\"pid\":611937000,\"type\":\"1.0_switch\",\"address\":\"FE000203\",\"opt\":\"00000001\",\"optName\":\"开启\",\"delay\":0},{\"id\":2,\"pid\":499192175,\"type\":\"5.0_timer\",\"address\":\"FE200001\",\"opt\":\"00000000\",\"optName\":\"定时关闭\",\"delay\":0}],\"falseDo\":[{\"id\":1,\"pid\":499192175,\"type\":\"5.0_timer\",\"address\":\"FE200001\",\"opt\":\"00000000\",\"optName\":\"定时关闭\",\"delay\":0},{\"id\":2,\"pid\":540085328,\"type\":\"6.1_panel\",\"address\":\"FE300001\",\"opt\":\"00000000\",\"optName\":\"禁止面板触发\",\"delay\":0}]}"
                    },
                    {
                        "id": 3,
                        "attr": 1,
                        "modelType": "VoiceDeal",
                        "content": null
                    }
                ],
                "id": 3,
                "pid": 144687686
            }
        ],
        "IP": "192.168.1.222",
        "Dev": "GW100A"
    },
    {
        "logics": [],
        "IP": "192.168.1.223",
        "Dev": "GW100A"
    }
]