[
    {
        "panels": [],
        "IP": null,
        "Dev": null
    },
    {
        "panels": [
            {
                "panelsInfo": [
                    {
                        "id": 1,
                        "pid": 945030246,
                        "keyAddress": "FE230001",
                        "objAddress": "FE000201",
                        "objType": "1.0_switch",
                        "opt": 1,
                        "showAddress": "FE000201",
                        "showMode": "同步"
                    },
                    {
                        "id": 2,
                        "pid": 975966521,
                        "keyAddress": "FE230002",
                        "objAddress": "FE000202",
                        "objType": "1.0_switch",
                        "opt": 1,
                        "showAddress": "FE000202",
                        "showMode": "同步"
                    },
                    {
                        "id": 3,
                        "pid": 723477596,
                        "keyAddress": "FE230003",
                        "objAddress": "FE000203",
                        "objType": "1.0_switch",
                        "opt": 1,
                        "showAddress": "FE000203",
                        "showMode": "同步"
                    },
                    {
                        "id": 4,
                        "pid": 708618717,
                        "keyAddress": "FE230004",
                        "objAddress": "FE000204",
                        "objType": "1.0_switch",
                        "opt": 1,
                        "showAddress": "FE000204",
                        "showMode": "同步"
                    },
                    {
                        "id": 5,
                        "pid": 910587455,
                        "keyAddress": "FE230005",
                        "objAddress": "FE000205",
                        "objType": "1.0_switch",
                        "opt": 1,
                        "showAddress": "FE000205",
                        "showMode": "同步"
                    },
                    {
                        "id": 6,
                        "pid": 406053114,
                        "keyAddress": "FE230006",
                        "objAddress": "FE000206",
                        "objType": "1.0_switch",
                        "opt": 1,
                        "showAddress": "FE000206",
                        "showMode": "同步"
                    },
                    {
                        "id": 7,
                        "pid": 0,
                        "keyAddress": "FE230007",
                        "objAddress": "",
                        "objType": "",
                        "opt": 255,
                        "showAddress": "",
                        "showMode": ""
                    },
                    {
                        "id": 8,
                        "pid": 0,
                        "keyAddress": "FE230008",
                        "objAddress": "",
                        "objType": "",
                        "opt": 255,
                        "showAddress": "",
                        "showMode": ""
                    },
                    {
                        "id": 257,
                        "pid": 0,
                        "keyAddress": "FE230101",
                        "objAddress": "",
                        "objType": "",
                        "opt": 255,
                        "showAddress": "",
                        "showMode": ""
                    },
                    {
                        "id": 258,
                        "pid": 0,
                        "keyAddress": "FE230102",
                        "objAddress": "",
                        "objType": "",
                        "opt": 255,
                        "showAddress": "",
                        "showMode": ""
                    },
                    {
                        "id": 259,
                        "pid": 0,
                        "keyAddress": "FE230103",
                        "objAddress": "",
                        "objType": "",
                        "opt": 255,
                        "showAddress": "",
                        "showMode": ""
                    },
                    {
                        "id": 260,
                        "pid": 0,
                        "keyAddress": "FE230104",
                        "objAddress": "",
                        "objType": "",
                        "opt": 255,
                        "showAddress": "",
                        "showMode": ""
                    },
                    {
                        "id": 261,
                        "pid": 0,
                        "keyAddress": "FE230105",
                        "objAddress": "",
                        "objType": "",
                        "opt": 255,
                        "showAddress": "",
                        "showMode": ""
                    },
                    {
                        "id": 262,
                        "pid": 0,
                        "keyAddress": "FE230106",
                        "objAddress": "",
                        "objType": "",
                        "opt": 255,
                        "showAddress": "",
                        "showMode": ""
                    },
                    {
                        "id": 263,
                        "pid": 0,
                        "keyAddress": "FE230107",
                        "objAddress": "",
                        "objType": "",
                        "opt": 255,
                        "showAddress": "",
                        "showMode": ""
                    },
                    {
                        "id": 264,
                        "pid": 0,
                        "keyAddress": "FE230108",
                        "objAddress": "",
                        "objType": "",
                        "opt": 255,
                        "showAddress": "",
                        "showMode": ""
                    },
                    {
                        "id": 513,
                        "pid": 0,
                        "keyAddress": "FE230201",
                        "objAddress": "",
                        "objType": "",
                        "opt": 255,
                        "showAddress": "",
                        "showMode": ""
                    },
                    {
                        "id": 514,
                        "pid": 0,
                        "keyAddress": "FE230202",
                        "objAddress": "",
                        "objType": "",
                        "opt": 255,
                        "showAddress": "",
                        "showMode": ""
                    },
                    {
                        "id": 515,
                        "pid": 0,
                        "keyAddress": "FE230203",
                        "objAddress": "",
                        "objType": "",
                        "opt": 255,
                        "showAddress": "",
                        "showMode": ""
                    },
                    {
                        "id": 516,
                        "pid": 0,
                        "keyAddress": "FE230204",
                        "objAddress": "",
                        "objType": "",
                        "opt": 255,
                        "showAddress": "",
                        "showMode": ""
                    },
                    {
                        "id": 517,
                        "pid": 0,
                        "keyAddress": "FE230205",
                        "objAddress": "",
                        "objType": "",
                        "opt": 255,
                        "showAddress": "",
                        "showMode": ""
                    },
                    {
                        "id": 518,
                        "pid": 0,
                        "keyAddress": "FE230206",
                        "objAddress": "",
                        "objType": "",
                        "opt": 255,
                        "showAddress": "",
                        "showMode": ""
                    },
                    {
                        "id": 519,
                        "pid": 0,
                        "keyAddress": "FE230207",
                        "objAddress": "",
                        "objType": "",
                        "opt": 255,
                        "showAddress": "",
                        "showMode": ""
                    },
                    {
                        "id": 520,
                        "pid": 0,
                        "keyAddress": "FE230208",
                        "objAddress": "",
                        "objType": "",
                        "opt": 255,
                        "showAddress": "",
                        "showMode": ""
                    },
                    {
                        "id": 769,
                        "pid": 0,
                        "keyAddress": "FE230301",
                        "objAddress": "",
                        "objType": "",
                        "opt": 255,
                        "showAddress": "",
                        "showMode": ""
                    },
                    {
                        "id": 770,
                        "pid": 0,
                        "keyAddress": "FE230302",
                        "objAddress": "",
                        "objType": "",
                        "opt": 255,
                        "showAddress": "",
                        "showMode": ""
                    },
                    {
                        "id": 771,
                        "pid": 0,
                        "keyAddress": "FE230303",
                        "objAddress": "",
                        "objType": "",
                        "opt": 255,
                        "showAddress": "",
                        "showMode": ""
                    },
                    {
                        "id": 772,
                        "pid": 0,
                        "keyAddress": "FE230304",
                        "objAddress": "",
                        "objType": "",
                        "opt": 255,
                        "showAddress": "",
                        "showMode": ""
                    },
                    {
                        "id": 773,
                        "pid": 0,
                        "keyAddress": "FE230305",
                        "objAddress": "",
                        "objType": "",
                        "opt": 255,
                        "showAddress": "",
                        "showMode": ""
                    },
                    {
                        "id": 774,
                        "pid": 0,
                        "keyAddress": "FE230306",
                        "objAddress": "",
                        "objType": "",
                        "opt": 255,
                        "showAddress": "",
                        "showMode": ""
                    },
                    {
                        "id": 775,
                        "pid": 0,
                        "keyAddress": "FE230307",
                        "objAddress": "",
                        "objType": "",
                        "opt": 255,
                        "showAddress": "",
                        "showMode": ""
                    },
                    {
                        "id": 776,
                        "pid": 0,
                        "keyAddress": "FE230308",
                        "objAddress": "",
                        "objType": "",
                        "opt": 255,
                        "showAddress": "",
                        "showMode": ""
                    },
                    {
                        "id": 1025,
                        "pid": 0,
                        "keyAddress": "FE230401",
                        "objAddress": "",
                        "objType": "",
                        "opt": 255,
                        "showAddress": "",
                        "showMode": ""
                    },
                    {
                        "id": 1026,
                        "pid": 0,
                        "keyAddress": "FE230402",
                        "objAddress": "",
                        "objType": "",
                        "opt": 255,
                        "showAddress": "",
                        "showMode": ""
                    },
                    {
                        "id": 1027,
                        "pid": 0,
                        "keyAddress": "FE230403",
                        "objAddress": "",
                        "objType": "",
                        "opt": 255,
                        "showAddress": "",
                        "showMode": ""
                    },
                    {
                        "id": 1028,
                        "pid": 0,
                        "keyAddress": "FE230404",
                        "objAddress": "",
                        "objType": "",
                        "opt": 255,
                        "showAddress": "",
                        "showMode": ""
                    },
                    {
                        "id": 1029,
                        "pid": 0,
                        "keyAddress": "FE230405",
                        "objAddress": "",
                        "objType": "",
                        "opt": 255,
                        "showAddress": "",
                        "showMode": ""
                    },
                    {
                        "id": 1030,
                        "pid": 0,
                        "keyAddress": "FE230406",
                        "objAddress": "",
                        "objType": "",
                        "opt": 255,
                        "showAddress": "",
                        "showMode": ""
                    },
                    {
                        "id": 1031,
                        "pid": 0,
                        "keyAddress": "FE230407",
                        "objAddress": "",
                        "objType": "",
                        "opt": 255,
                        "showAddress": "",
                        "showMode": ""
                    },
                    {
                        "id": 1032,
                        "pid": 0,
                        "keyAddress": "FE230408",
                        "objAddress": "",
                        "objType": "",
                        "opt": 255,
                        "showAddress": "",
                        "showMode": ""
                    },
                    {
                        "id": 1281,
                        "pid": 0,
                        "keyAddress": "FE230501",
                        "objAddress": "",
                        "objType": "",
                        "opt": 255,
                        "showAddress": "",
                        "showMode": ""
                    },
                    {
                        "id": 1282,
                        "pid": 0,
                        "keyAddress": "FE230502",
                        "objAddress": "",
                        "objType": "",
                        "opt": 255,
                        "showAddress": "",
                        "showMode": ""
                    },
                    {
                        "id": 1283,
                        "pid": 0,
                        "keyAddress": "FE230503",
                        "objAddress": "",
                        "objType": "",
                        "opt": 255,
                        "showAddress": "",
                        "showMode": ""
                    },
                    {
                        "id": 1284,
                        "pid": 0,
                        "keyAddress": "FE230504",
                        "objAddress": "",
                        "objType": "",
                        "opt": 255,
                        "showAddress": "",
                        "showMode": ""
                    },
                    {
                        "id": 1285,
                        "pid": 0,
                        "keyAddress": "FE230505",
                        "objAddress": "",
                        "objType": "",
                        "opt": 255,
                        "showAddress": "",
                        "showMode": ""
                    },
                    {
                        "id": 1286,
                        "pid": 0,
                        "keyAddress": "FE230506",
                        "objAddress": "",
                        "objType": "",
                        "opt": 255,
                        "showAddress": "",
                        "showMode": ""
                    },
                    {
                        "id": 1287,
                        "pid": 0,
                        "keyAddress": "FE230507",
                        "objAddress": "",
                        "objType": "",
                        "opt": 255,
                        "showAddress": "",
                        "showMode": ""
                    },
                    {
                        "id": 1288,
                        "pid": 0,
                        "keyAddress": "FE230508",
                        "objAddress": "",
                        "objType": "",
                        "opt": 255,
                        "showAddress": "",
                        "showMode": ""
                    },
                    {
                        "id": 1537,
                        "pid": 0,
                        "keyAddress": "FE230601",
                        "objAddress": "",
                        "objType": "",
                        "opt": 255,
                        "showAddress": "",
                        "showMode": ""
                    },
                    {
                        "id": 1538,
                        "pid": 0,
                        "keyAddress": "FE230602",
                        "objAddress": "",
                        "objType": "",
                        "opt": 255,
                        "showAddress": "",
                        "showMode": ""
                    },
                    {
                        "id": 1539,
                        "pid": 0,
                        "keyAddress": "FE230603",
                        "objAddress": "",
                        "objType": "",
                        "opt": 255,
                        "showAddress": "",
                        "showMode": ""
                    },
                    {
                        "id": 1540,
                        "pid": 0,
                        "keyAddress": "FE230604",
                        "objAddress": "",
                        "objType": "",
                        "opt": 255,
                        "showAddress": "",
                        "showMode": ""
                    },
                    {
                        "id": 1541,
                        "pid": 0,
                        "keyAddress": "FE230605",
                        "objAddress": "",
                        "objType": "",
                        "opt": 255,
                        "showAddress": "",
                        "showMode": ""
                    },
                    {
                        "id": 1542,
                        "pid": 0,
                        "keyAddress": "FE230606",
                        "objAddress": "",
                        "objType": "",
                        "opt": 255,
                        "showAddress": "",
                        "showMode": ""
                    },
                    {
                        "id": 1543,
                        "pid": 0,
                        "keyAddress": "FE230607",
                        "objAddress": "",
                        "objType": "",
                        "opt": 255,
                        "showAddress": "",
                        "showMode": ""
                    },
                    {
                        "id": 1544,
                        "pid": 0,
                        "keyAddress": "FE230608",
                        "objAddress": "",
                        "objType": "",
                        "opt": 255,
                        "showAddress": "",
                        "showMode": ""
                    },
                    {
                        "id": 1793,
                        "pid": 0,
                        "keyAddress": "FE230701",
                        "objAddress": "",
                        "objType": "",
                        "opt": 255,
                        "showAddress": "",
                        "showMode": ""
                    },
                    {
                        "id": 1794,
                        "pid": 0,
                        "keyAddress": "FE230702",
                        "objAddress": "",
                        "objType": "",
                        "opt": 255,
                        "showAddress": "",
                        "showMode": ""
                    },
                    {
                        "id": 1795,
                        "pid": 0,
                        "keyAddress": "FE230703",
                        "objAddress": "",
                        "objType": "",
                        "opt": 255,
                        "showAddress": "",
                        "showMode": ""
                    },
                    {
                        "id": 1796,
                        "pid": 0,
                        "keyAddress": "FE230704",
                        "objAddress": "",
                        "objType": "",
                        "opt": 255,
                        "showAddress": "",
                        "showMode": ""
                    },
                    {
                        "id": 1797,
                        "pid": 0,
                        "keyAddress": "FE230705",
                        "objAddress": "",
                        "objType": "",
                        "opt": 255,
                        "showAddress": "",
                        "showMode": ""
                    },
                    {
                        "id": 1798,
                        "pid": 0,
                        "keyAddress": "FE230706",
                        "objAddress": "",
                        "objType": "",
                        "opt": 255,
                        "showAddress": "",
                        "showMode": ""
                    },
                    {
                        "id": 1799,
                        "pid": 0,
                        "keyAddress": "FE230707",
                        "objAddress": "",
                        "objType": "",
                        "opt": 255,
                        "showAddress": "",
                        "showMode": ""
                    },
                    {
                        "id": 1800,
                        "pid": 0,
                        "keyAddress": "FE230708",
                        "objAddress": "",
                        "objType": "",
                        "opt": 255,
                        "showAddress": "",
                        "showMode": ""
                    },
                    {
                        "id": 2049,
                        "pid": 0,
                        "keyAddress": "FE230801",
                        "objAddress": "",
                        "objType": "",
                        "opt": 255,
                        "showAddress": "",
                        "showMode": ""
                    },
                    {
                        "id": 2050,
                        "pid": 0,
                        "keyAddress": "FE230802",
                        "objAddress": "",
                        "objType": "",
                        "opt": 255,
                        "showAddress": "",
                        "showMode": ""
                    },
                    {
                        "id": 2051,
                        "pid": 0,
                        "keyAddress": "FE230803",
                        "objAddress": "",
                        "objType": "",
                        "opt": 255,
                        "showAddress": "",
                        "showMode": ""
                    },
                    {
                        "id": 2052,
                        "pid": 0,
                        "keyAddress": "FE230804",
                        "objAddress": "",
                        "objType": "",
                        "opt": 255,
                        "showAddress": "",
                        "showMode": ""
                    },
                    {
                        "id": 2053,
                        "pid": 0,
                        "keyAddress": "FE230805",
                        "objAddress": "",
                        "objType": "",
                        "opt": 255,
                        "showAddress": "",
                        "showMode": ""
                    },
                    {
                        "id": 2054,
                        "pid": 0,
                        "keyAddress": "FE230806",
                        "objAddress": "",
                        "objType": "",
                        "opt": 255,
                        "showAddress": "",
                        "showMode": ""
                    },
                    {
                        "id": 2055,
                        "pid": 0,
                        "keyAddress": "FE230807",
                        "objAddress": "",
                        "objType": "",
                        "opt": 255,
                        "showAddress": "",
                        "showMode": ""
                    },
                    {
                        "id": 2056,
                        "pid": 0,
                        "keyAddress": "FE230808",
                        "objAddress": "",
                        "objType": "",
                        "opt": 255,
                        "showAddress": "",
                        "showMode": ""
                    },
                    {
                        "id": 2305,
                        "pid": 0,
                        "keyAddress": "FE230901",
                        "objAddress": "",
                        "objType": "",
                        "opt": 255,
                        "showAddress": "",
                        "showMode": ""
                    },
                    {
                        "id": 2306,
                        "pid": 0,
                        "keyAddress": "FE230902",
                        "objAddress": "",
                        "objType": "",
                        "opt": 255,
                        "showAddress": "",
                        "showMode": ""
                    },
                    {
                        "id": 2307,
                        "pid": 0,
                        "keyAddress": "FE230903",
                        "objAddress": "",
                        "objType": "",
                        "opt": 255,
                        "showAddress": "",
                        "showMode": ""
                    },
                    {
                        "id": 2308,
                        "pid": 0,
                        "keyAddress": "FE230904",
                        "objAddress": "",
                        "objType": "",
                        "opt": 255,
                        "showAddress": "",
                        "showMode": ""
                    },
                    {
                        "id": 2309,
                        "pid": 0,
                        "keyAddress": "FE230905",
                        "objAddress": "",
                        "objType": "",
                        "opt": 255,
                        "showAddress": "",
                        "showMode": ""
                    },
                    {
                        "id": 2310,
                        "pid": 0,
                        "keyAddress": "FE230906",
                        "objAddress": "",
                        "objType": "",
                        "opt": 255,
                        "showAddress": "",
                        "showMode": ""
                    },
                    {
                        "id": 2311,
                        "pid": 0,
                        "keyAddress": "FE230907",
                        "objAddress": "",
                        "objType": "",
                        "opt": 255,
                        "showAddress": "",
                        "showMode": ""
                    },
                    {
                        "id": 2312,
                        "pid": 0,
                        "keyAddress": "FE230908",
                        "objAddress": "",
                        "objType": "",
                        "opt": 255,
                        "showAddress": "",
                        "showMode": ""
                    }
                ],
                "id": 35,
                "pid": 479068832
            },
            {
                "panelsInfo": [
                    {
                        "id": 1,
                        "pid": 893954542,
                        "keyAddress": "FE3F0001",
                        "objAddress": "FE000301",
                        "objType": "1.0_switch",
                        "opt": 1,
                        "showAddress": "FE000301",
                        "showMode": "同步"
                    },
                    {
                        "id": 2,
                        "pid": 612191369,
                        "keyAddress": "FE3F0002",
                        "objAddress": "FE000302",
                        "objType": "1.0_switch",
                        "opt": 1,
                        "showAddress": "FE000302",
                        "showMode": "同步"
                    },
                    {
                        "id": 3,
                        "pid": 871842363,
                        "keyAddress": "FE3F0003",
                        "objAddress": "FE000303",
                        "objType": "1.0_switch",
                        "opt": 1,
                        "showAddress": "FE000303",
                        "showMode": "同步"
                    },
                    {
                        "id": 4,
                        "pid": 611747860,
                        "keyAddress": "FE3F0004",
                        "objAddress": "FE000304",
                        "objType": "1.0_switch",
                        "opt": 1,
                        "showAddress": "FE000304",
                        "showMode": "同步"
                    },
                    {
                        "id": 5,
                        "pid": 760091851,
                        "keyAddress": "FE3F0005",
                        "objAddress": "FE000305",
                        "objType": "1.0_switch",
                        "opt": 1,
                        "showAddress": "FE000305",
                        "showMode": "同步"
                    },
                    {
                        "id": 6,
                        "pid": 305634188,
                        "keyAddress": "FE3F0006",
                        "objAddress": "FE000306",
                        "objType": "1.0_switch",
                        "opt": 1,
                        "showAddress": "FE000306",
                        "showMode": "同步"
                    },
                    {
                        "id": 257,
                        "pid": 0,
                        "keyAddress": "FE3F0101",
                        "objAddress": "",
                        "objType": "",
                        "opt": 255,
                        "showAddress": "",
                        "showMode": ""
                    },
                    {
                        "id": 258,
                        "pid": 0,
                        "keyAddress": "FE3F0102",
                        "objAddress": "",
                        "objType": "",
                        "opt": 255,
                        "showAddress": "",
                        "showMode": ""
                    },
                    {
                        "id": 259,
                        "pid": 0,
                        "keyAddress": "FE3F0103",
                        "objAddress": "",
                        "objType": "",
                        "opt": 255,
                        "showAddress": "",
                        "showMode": ""
                    },
                    {
                        "id": 260,
                        "pid": 0,
                        "keyAddress": "FE3F0104",
                        "objAddress": "",
                        "objType": "",
                        "opt": 255,
                        "showAddress": "",
                        "showMode": ""
                    },
                    {
                        "id": 261,
                        "pid": 0,
                        "keyAddress": "FE3F0105",
                        "objAddress": "",
                        "objType": "",
                        "opt": 255,
                        "showAddress": "",
                        "showMode": ""
                    },
                    {
                        "id": 262,
                        "pid": 0,
                        "keyAddress": "FE3F0106",
                        "objAddress": "",
                        "objType": "",
                        "opt": 255,
                        "showAddress": "",
                        "showMode": ""
                    },
                    {
                        "id": 513,
                        "pid": 0,
                        "keyAddress": "FE3F0201",
                        "objAddress": "",
                        "objType": "",
                        "opt": 255,
                        "showAddress": "",
                        "showMode": ""
                    },
                    {
                        "id": 514,
                        "pid": 0,
                        "keyAddress": "FE3F0202",
                        "objAddress": "",
                        "objType": "",
                        "opt": 255,
                        "showAddress": "",
                        "showMode": ""
                    },
                    {
                        "id": 515,
                        "pid": 0,
                        "keyAddress": "FE3F0203",
                        "objAddress": "",
                        "objType": "",
                        "opt": 255,
                        "showAddress": "",
                        "showMode": ""
                    },
                    {
                        "id": 516,
                        "pid": 0,
                        "keyAddress": "FE3F0204",
                        "objAddress": "",
                        "objType": "",
                        "opt": 255,
                        "showAddress": "",
                        "showMode": ""
                    },
                    {
                        "id": 517,
                        "pid": 0,
                        "keyAddress": "FE3F0205",
                        "objAddress": "",
                        "objType": "",
                        "opt": 255,
                        "showAddress": "",
                        "showMode": ""
                    },
                    {
                        "id": 518,
                        "pid": 0,
                        "keyAddress": "FE3F0206",
                        "objAddress": "",
                        "objType": "",
                        "opt": 255,
                        "showAddress": "",
                        "showMode": ""
                    },
                    {
                        "id": 769,
                        "pid": 0,
                        "keyAddress": "FE3F0301",
                        "objAddress": "",
                        "objType": "",
                        "opt": 255,
                        "showAddress": "",
                        "showMode": ""
                    },
                    {
                        "id": 770,
                        "pid": 0,
                        "keyAddress": "FE3F0302",
                        "objAddress": "",
                        "objType": "",
                        "opt": 255,
                        "showAddress": "",
                        "showMode": ""
                    },
                    {
                        "id": 771,
                        "pid": 0,
                        "keyAddress": "FE3F0303",
                        "objAddress": "",
                        "objType": "",
                        "opt": 255,
                        "showAddress": "",
                        "showMode": ""
                    },
                    {
                        "id": 772,
                        "pid": 0,
                        "keyAddress": "FE3F0304",
                        "objAddress": "",
                        "objType": "",
                        "opt": 255,
                        "showAddress": "",
                        "showMode": ""
                    },
                    {
                        "id": 773,
                        "pid": 0,
                        "keyAddress": "FE3F0305",
                        "objAddress": "",
                        "objType": "",
                        "opt": 255,
                        "showAddress": "",
                        "showMode": ""
                    },
                    {
                        "id": 774,
                        "pid": 0,
                        "keyAddress": "FE3F0306",
                        "objAddress": "",
                        "objType": "",
                        "opt": 255,
                        "showAddress": "",
                        "showMode": ""
                    },
                    {
                        "id": 1025,
                        "pid": 0,
                        "keyAddress": "FE3F0401",
                        "objAddress": "",
                        "objType": "",
                        "opt": 255,
                        "showAddress": "",
                        "showMode": ""
                    },
                    {
                        "id": 1026,
                        "pid": 0,
                        "keyAddress": "FE3F0402",
                        "objAddress": "",
                        "objType": "",
                        "opt": 255,
                        "showAddress": "",
                        "showMode": ""
                    },
                    {
                        "id": 1027,
                        "pid": 0,
                        "keyAddress": "FE3F0403",
                        "objAddress": "",
                        "objType": "",
                        "opt": 255,
                        "showAddress": "",
                        "showMode": ""
                    },
                    {
                        "id": 1028,
                        "pid": 0,
                        "keyAddress": "FE3F0404",
                        "objAddress": "",
                        "objType": "",
                        "opt": 255,
                        "showAddress": "",
                        "showMode": ""
                    },
                    {
                        "id": 1029,
                        "pid": 0,
                        "keyAddress": "FE3F0405",
                        "objAddress": "",
                        "objType": "",
                        "opt": 255,
                        "showAddress": "",
                        "showMode": ""
                    },
                    {
                        "id": 1030,
                        "pid": 0,
                        "keyAddress": "FE3F0406",
                        "objAddress": "",
                        "objType": "",
                        "opt": 255,
                        "showAddress": "",
                        "showMode": ""
                    },
                    {
                        "id": 1281,
                        "pid": 0,
                        "keyAddress": "FE3F0501",
                        "objAddress": "",
                        "objType": "",
                        "opt": 255,
                        "showAddress": "",
                        "showMode": ""
                    },
                    {
                        "id": 1282,
                        "pid": 0,
                        "keyAddress": "FE3F0502",
                        "objAddress": "",
                        "objType": "",
                        "opt": 255,
                        "showAddress": "",
                        "showMode": ""
                    },
                    {
                        "id": 1283,
                        "pid": 0,
                        "keyAddress": "FE3F0503",
                        "objAddress": "",
                        "objType": "",
                        "opt": 255,
                        "showAddress": "",
                        "showMode": ""
                    },
                    {
                        "id": 1284,
                        "pid": 0,
                        "keyAddress": "FE3F0504",
                        "objAddress": "",
                        "objType": "",
                        "opt": 255,
                        "showAddress": "",
                        "showMode": ""
                    },
                    {
                        "id": 1285,
                        "pid": 0,
                        "keyAddress": "FE3F0505",
                        "objAddress": "",
                        "objType": "",
                        "opt": 255,
                        "showAddress": "",
                        "showMode": ""
                    },
                    {
                        "id": 1286,
                        "pid": 0,
                        "keyAddress": "FE3F0506",
                        "objAddress": "",
                        "objType": "",
                        "opt": 255,
                        "showAddress": "",
                        "showMode": ""
                    },
                    {
                        "id": 1537,
                        "pid": 0,
                        "keyAddress": "FE3F0601",
                        "objAddress": "",
                        "objType": "",
                        "opt": 255,
                        "showAddress": "",
                        "showMode": ""
                    },
                    {
                        "id": 1538,
                        "pid": 0,
                        "keyAddress": "FE3F0602",
                        "objAddress": "",
                        "objType": "",
                        "opt": 255,
                        "showAddress": "",
                        "showMode": ""
                    },
                    {
                        "id": 1539,
                        "pid": 0,
                        "keyAddress": "FE3F0603",
                        "objAddress": "",
                        "objType": "",
                        "opt": 255,
                        "showAddress": "",
                        "showMode": ""
                    },
                    {
                        "id": 1540,
                        "pid": 0,
                        "keyAddress": "FE3F0604",
                        "objAddress": "",
                        "objType": "",
                        "opt": 255,
                        "showAddress": "",
                        "showMode": ""
                    },
                    {
                        "id": 1541,
                        "pid": 0,
                        "keyAddress": "FE3F0605",
                        "objAddress": "",
                        "objType": "",
                        "opt": 255,
                        "showAddress": "",
                        "showMode": ""
                    },
                    {
                        "id": 1542,
                        "pid": 0,
                        "keyAddress": "FE3F0606",
                        "objAddress": "",
                        "objType": "",
                        "opt": 255,
                        "showAddress": "",
                        "showMode": ""
                    },
                    {
                        "id": 1793,
                        "pid": 0,
                        "keyAddress": "FE3F0701",
                        "objAddress": "",
                        "objType": "",
                        "opt": 255,
                        "showAddress": "",
                        "showMode": ""
                    },
                    {
                        "id": 1794,
                        "pid": 0,
                        "keyAddress": "FE3F0702",
                        "objAddress": "",
                        "objType": "",
                        "opt": 255,
                        "showAddress": "",
                        "showMode": ""
                    },
                    {
                        "id": 1795,
                        "pid": 0,
                        "keyAddress": "FE3F0703",
                        "objAddress": "",
                        "objType": "",
                        "opt": 255,
                        "showAddress": "",
                        "showMode": ""
                    },
                    {
                        "id": 1796,
                        "pid": 0,
                        "keyAddress": "FE3F0704",
                        "objAddress": "",
                        "objType": "",
                        "opt": 255,
                        "showAddress": "",
                        "showMode": ""
                    },
                    {
                        "id": 1797,
                        "pid": 0,
                        "keyAddress": "FE3F0705",
                        "objAddress": "",
                        "objType": "",
                        "opt": 255,
                        "showAddress": "",
                        "showMode": ""
                    },
                    {
                        "id": 1798,
                        "pid": 0,
                        "keyAddress": "FE3F0706",
                        "objAddress": "",
                        "objType": "",
                        "opt": 255,
                        "showAddress": "",
                        "showMode": ""
                    },
                    {
                        "id": 2049,
                        "pid": 0,
                        "keyAddress": "FE3F0801",
                        "objAddress": "",
                        "objType": "",
                        "opt": 255,
                        "showAddress": "",
                        "showMode": ""
                    },
                    {
                        "id": 2050,
                        "pid": 0,
                        "keyAddress": "FE3F0802",
                        "objAddress": "",
                        "objType": "",
                        "opt": 255,
                        "showAddress": "",
                        "showMode": ""
                    },
                    {
                        "id": 2051,
                        "pid": 0,
                        "keyAddress": "FE3F0803",
                        "objAddress": "",
                        "objType": "",
                        "opt": 255,
                        "showAddress": "",
                        "showMode": ""
                    },
                    {
                        "id": 2052,
                        "pid": 0,
                        "keyAddress": "FE3F0804",
                        "objAddress": "",
                        "objType": "",
                        "opt": 255,
                        "showAddress": "",
                        "showMode": ""
                    },
                    {
                        "id": 2053,
                        "pid": 0,
                        "keyAddress": "FE3F0805",
                        "objAddress": "",
                        "objType": "",
                        "opt": 255,
                        "showAddress": "",
                        "showMode": ""
                    },
                    {
                        "id": 2054,
                        "pid": 0,
                        "keyAddress": "FE3F0806",
                        "objAddress": "",
                        "objType": "",
                        "opt": 255,
                        "showAddress": "",
                        "showMode": ""
                    },
                    {
                        "id": 2305,
                        "pid": 0,
                        "keyAddress": "FE3F0901",
                        "objAddress": "",
                        "objType": "",
                        "opt": 255,
                        "showAddress": "",
                        "showMode": ""
                    },
                    {
                        "id": 2306,
                        "pid": 0,
                        "keyAddress": "FE3F0902",
                        "objAddress": "",
                        "objType": "",
                        "opt": 255,
                        "showAddress": "",
                        "showMode": ""
                    },
                    {
                        "id": 2307,
                        "pid": 0,
                        "keyAddress": "FE3F0903",
                        "objAddress": "",
                        "objType": "",
                        "opt": 255,
                        "showAddress": "",
                        "showMode": ""
                    },
                    {
                        "id": 2308,
                        "pid": 0,
                        "keyAddress": "FE3F0904",
                        "objAddress": "",
                        "objType": "",
                        "opt": 255,
                        "showAddress": "",
                        "showMode": ""
                    },
                    {
                        "id": 2309,
                        "pid": 0,
                        "keyAddress": "FE3F0905",
                        "objAddress": "",
                        "objType": "",
                        "opt": 255,
                        "showAddress": "",
                        "showMode": ""
                    },
                    {
                        "id": 2310,
                        "pid": 0,
                        "keyAddress": "FE3F0906",
                        "objAddress": "",
                        "objType": "",
                        "opt": 255,
                        "showAddress": "",
                        "showMode": ""
                    }
                ],
                "id": 63,
                "pid": 218530821
            },
            {
                "panelsInfo": [
                    {
                        "id": 1,
                        "pid": 0,
                        "keyAddress": "",
                        "objAddress": "",
                        "objType": "",
                        "opt": 255,
                        "showAddress": "",
                        "showMode": ""
                    },
                    {
                        "id": 2,
                        "pid": 0,
                        "keyAddress": "",
                        "objAddress": "",
                        "objType": "",
                        "opt": 255,
                        "showAddress": "",
                        "showMode": ""
                    }
                ],
                "id": 101,
                "pid": 758555603
            },
            {
                "panelsInfo": [],
                "id": 102,
                "pid": 743696725
            },
            {
                "panelsInfo": [],
                "id": 103,
                "pid": 713978968
            },
            {
                "panelsInfo": [],
                "id": 104,
                "pid": 141537295
            },
            {
                "panelsInfo": [],
                "id": 105,
                "pid": 217916445
            },
            {
                "panelsInfo": [],
                "id": 106,
                "pid": 701648356
            },
            {
                "panelsInfo": [],
                "id": 107,
                "pid": 773745982
            },
            {
                "panelsInfo": [],
                "id": 108,
                "pid": 530172384
            },
            {
                "panelsInfo": [],
                "id": 109,
                "pid": 685036220
            },
            {
                "panelsInfo": [],
                "id": 110,
                "pid": 488124016
            },
            {
                "panelsInfo": [],
                "id": 111,
                "pid": 598854725
            }
        ],
        "IP": "192.168.1.96",
        "Dev": "GW100A"
    }
]